{
  "date": "2026-07-01",
  "date_label": "Rabu, 1 Juli 2026",
  "count": 7,
  "jobs": [
    {
      "id": 3305,
      "company": "Alfamart",
      "title": "Crew Store (Kasir / Pramuniaga)",
      "blogger_url": "https://www.mintainfo.com/2026/07/rekrutmen-crew-store-kasir-pramuniaga_0807956623.html"
    },
    {
      "id": 3304,
      "company": "Alfamart",
      "title": "Crew Store (Kasir / Pramuniaga)",
      "blogger_url": "https://www.mintainfo.com/2026/07/rekrutmen-crew-store-kasir-pramuniaga.html"
    },
    {
      "id": 3303,
      "company": "Momoyo",
      "title": "Barista",
      "blogger_url": "https://www.mintainfo.com/2026/07/loker-barista-terbaru-momoyo-pekanbaru.html"
    },
    {
      "id": 3302,
      "company": "Sushi Yay!",
      "title": "Store Manager",
      "blogger_url": "https://www.mintainfo.com/2026/07/rekrutmen-store-manager-di-sushi-yay.html"
    },
    {
      "id": 3301,
      "company": "PT. Cakrawala Sari Cemerlang.",
      "title": "Admin Accounting (Pria)",
      "blogger_url": "https://www.mintainfo.com/2026/07/pt-cakrawala-sari-cemerlang-buka.html"
    },
    {
      "id": 3274,
      "company": "Pisang Keju 89",
      "title": "Karyawan",
      "blogger_url": "https://www.mintainfo.com/2026/07/loker-karyawan-terbaru-pisang-keju-89.html"
    },
    {
      "id": 3219,
      "company": "Dadarin Aja",
      "title": "Manager Restoran",
      "blogger_url": "https://www.mintainfo.com/2026/07/rekrutmen-manager-restoran-di-dadarin.html"
    }
  ]
}